tbc_video_export/__init__.py
tbc_video_export/__main__.py
tbc_video_export/common/__init__.py
tbc_video_export/common/consts.py
tbc_video_export/common/enums.py
tbc_video_export/common/exceptions.py
tbc_video_export/common/file_helper.py
tbc_video_export/common/tbc_json_helper.py
tbc_video_export/common/utils/__init__.py
tbc_video_export/common/utils/ansi.py
tbc_video_export/common/utils/files.py
tbc_video_export/common/utils/flatlist.py
tbc_video_export/common/utils/interrupts.py
tbc_video_export/common/utils/log.py
tbc_video_export/common/utils/metadata.py
tbc_video_export/common/utils/strings.py
tbc_video_export/common/utils/win32.py
tbc_video_export/common/video_system.py
tbc_video_export/config/__init__.py
tbc_video_export/config/config.py
tbc_video_export/config/default.py
tbc_video_export/config/json.py
tbc_video_export/config/profile.py
tbc_video_export/opts/__init__.py
tbc_video_export/opts/opt_actions.py
tbc_video_export/opts/opt_types.py
tbc_video_export/opts/opt_validators.py
tbc_video_export/opts/opts.py
tbc_video_export/opts/opts_ffmpeg.py
tbc_video_export/opts/opts_ldtools.py
tbc_video_export/opts/opts_parser.py
tbc_video_export/opts/opts_profile.py
tbc_video_export/process/__init__.py
tbc_video_export/process/parser/__init__.py
tbc_video_export/process/parser/export_state.py
tbc_video_export/process/parser/parser.py
tbc_video_export/process/parser/parser_factory.py
tbc_video_export/process/parser/parser_ffmpeg.py
tbc_video_export/process/parser/parser_ld_chroma_decoder.py
tbc_video_export/process/parser/parser_ld_dropout_correct.py
tbc_video_export/process/parser/parser_ld_export_metadata.py
tbc_video_export/process/parser/parser_ld_process_efm.py
tbc_video_export/process/parser/parser_ld_process_vbi.py
tbc_video_export/process/process.py
tbc_video_export/process/process_handler.py
tbc_video_export/process/process_state.py
tbc_video_export/process/progress_handler.py
tbc_video_export/process/wrapper/__init__.py
tbc_video_export-0.1.8.dist-info/LICENSE
tbc_video_export-0.1.8.dist-info/METADATA
tbc_video_export-0.1.8.dist-info/WHEEL
tbc_video_export-0.1.8.dist-info/entry_points.txt
tbc_video_export-0.1.8.dist-info/RECORD
