Metadata-Version: 2.3
Name: tbc-video-export
Version: 0.1.8
Summary: Tool for exporting S-Video and CVBS-type TBCs to video files.
License: GPL-3.0-or-later
Keywords: vhs-decode,ld-decode,cvbs-decode,tbc,rf capture
Author: Jitterbug
Author-email: jitterbug@posteo.co.uk
Maintainer: Jitterbug
Maintainer-email: jitterbug@posteo.co.uk
Requires-Python: >=3.10,<3.14
Classifier: License :: OSI Approved :: GNU General Public License v3 or later (GPLv3+)
Classifier: Programming Language :: Python :: 3
Classifier: Programming Language :: Python :: 3.10
Classifier: Programming Language :: Python :: 3.11
Classifier: Programming Language :: Python :: 3.12
Classifier: Programming Language :: Python :: 3.13
Requires-Dist: pywin32 (>=306,<307) ; sys_platform == "win32"
Requires-Dist: typing-extensions (>=4.10.0,<5.0.0)
Project-URL: Discord, https://discord.com/invite/pVVrrxd
Project-URL: Issues, https://github.com/JuniorIsAJitterbug/tbc-video-export/issues
Project-URL: Repository, https://github.com/JuniorIsAJitterbug/tbc-video-export
Project-URL: Wiki, https://github.com/JuniorIsAJitterbug/tbc-video-export/wiki
